Metadata-Version: 2.1
Name: flake8-sleep
Version: 0.0.1
Summary: flake8 plugin which checks that there is no use of sleep in the code.
Home-page: https://github.com/experquiz/flake8-sleep
Author: Nathan Malnoury
Author-email: nathan.malnoury@experquiz.com
License: MIT
Platform: UNKNOWN
Classifier: License :: OSI Approved :: MIT License
Classifier: Programming Language :: Python :: 3
Classifier: Programming Language :: Python :: 3 :: Only
Classifier: Programming Language :: Python :: 3.6
Classifier: Programming Language :: Python :: 3.7
Classifier: Programming Language :: Python :: 3.8
Requires-Python: >=3.6.1
